snowbird/__init__.py
snowbird/app.py
snowbird/command.py
snowbird/loader.py
snowbird/models.py
snowbird/resources.py
snowbird/utils.py
snowbird-0.0.3.dist-info/entry_points.txt
snowbird-0.0.3.dist-info/WHEEL
snowbird-0.0.3.dist-info/METADATA
snowbird-0.0.3.dist-info/RECORD
